[{"id":1,"coreId":"151","launchId":"63aa7636-d2b7-457f-a3e6-27e564e42941","flightNumber":15,"flightProven":1,"landingAttempt":1,"landingSuccess":1,"landingType":null,"landingLocation":"A Shortfall of Gravitas","turnaroundDays":23,"createdAt":"2026-04-10T21:25:41.029+00:00"},
{"id":2,"coreId":"101","launchId":"10fbecb2-7624-44bc-85ce-9a22b9b9f2ec","flightNumber":34,"flightProven":1,"landingAttempt":1,"landingSuccess":1,"landingType":null,"landingLocation":"Just Read the Instructions","turnaroundDays":37,"createdAt":"2026-04-10T21:25:41.050+00:00"},
{"id":3,"coreId":"193","launchId":"fd4ba54a-df30-4318-a79b-2f9d6a38acc5","flightNumber":12,"flightProven":1,"landingAttempt":1,"landingSuccess":1,"landingType":null,"landingLocation":"Of Course I Still Love You","turnaroundDays":33,"createdAt":"2026-04-10T21:25:41.058+00:00"},
{"id":4,"coreId":"124","launchId":"37dd4870-43df-4a28-9d14-0e088ddc1d2a","flightNumber":23,"flightProven":1,"landingAttempt":1,"landingSuccess":1,"landingType":null,"landingLocation":"Of Course I Still Love You","turnaroundDays":40,"createdAt":"2026-04-10T21:25:41.078+00:00"},
{"id":5,"coreId":"120","launchId":"2ab15fcb-7a74-429d-bab0-43635b723cfd","flightNumber":27,"flightProven":1,"landingAttempt":1,"landingSuccess":1,"landingType":null,"landingLocation":"A Shortfall of Gravitas","turnaroundDays":20,"createdAt":"2026-04-10T21:25:41.099+00:00"},
{"id":6,"coreId":"239","launchId":"1ca3ea18-b25b-4aad-9f6a-60a6434a8fa7","flightNumber":4,"flightProven":1,"landingAttempt":1,"landingSuccess":1,"landingType":null,"landingLocation":"Of Course I Still Love You","turnaroundDays":37,"createdAt":"2026-04-10T21:25:41.112+00:00"},
{"id":7,"coreId":"116","launchId":"890f714a-aa3c-487f-ae81-b7e654276cd5","flightNumber":27,"flightProven":1,"landingAttempt":1,"landingSuccess":1,"landingType":null,"landingLocation":"Just Read the Instructions","turnaroundDays":28,"createdAt":"2026-04-10T21:25:41.122+00:00"},
{"id":8,"coreId":"190","launchId":"f5df8e48-7612-4757-bd1b-cdb5b5a1936b","flightNumber":11,"flightProven":1,"landingAttempt":1,"landingSuccess":1,"landingType":null,"landingLocation":"A Shortfall of Gravitas","turnaroundDays":29,"createdAt":"2026-04-10T21:25:41.129+00:00"},
{"id":9,"coreId":"153","launchId":"42e15d83-d3b0-469d-9d58-580d242f364f","flightNumber":14,"flightProven":1,"landingAttempt":1,"landingSuccess":1,"landingType":null,"landingLocation":"Of Course I Still Love You","turnaroundDays":37,"createdAt":"2026-04-10T21:25:41.135+00:00"}]
